odoo/addons/helpdesk_ticket_massive_creation/CHANGELOG.md
odoo/addons/helpdesk_ticket_massive_creation/README.rst
odoo/addons/helpdesk_ticket_massive_creation/__init__.py
odoo/addons/helpdesk_ticket_massive_creation/__manifest__.py
odoo/addons/helpdesk_ticket_massive_creation/i18n/ca_ES.po
odoo/addons/helpdesk_ticket_massive_creation/i18n/es.po
odoo/addons/helpdesk_ticket_massive_creation/static/description/icon.png
odoo/addons/helpdesk_ticket_massive_creation/tests/__init__.py
odoo/addons/helpdesk_ticket_massive_creation/tests/test_helpdesk_ticket_massive_creation_wizard.py
odoo/addons/helpdesk_ticket_massive_creation/wizards/__init__.py
odoo/addons/helpdesk_ticket_massive_creation/wizards/helpdesk_ticket_massive_creation/__init__.py
odoo/addons/helpdesk_ticket_massive_creation/wizards/helpdesk_ticket_massive_creation/helpdesk_ticket_massive_creation.py
odoo/addons/helpdesk_ticket_massive_creation/wizards/helpdesk_ticket_massive_creation/helpdesk_ticket_massive_creation.xml
odoo12_addon_helpdesk_ticket_massive_creation-12.0.0.3.1.dist-info/METADATA
odoo12_addon_helpdesk_ticket_massive_creation-12.0.0.3.1.dist-info/WHEEL
odoo12_addon_helpdesk_ticket_massive_creation-12.0.0.3.1.dist-info/top_level.txt
odoo12_addon_helpdesk_ticket_massive_creation-12.0.0.3.1.dist-info/RECORD
